downleth/__init__.py
downleth/__main__.py
downleth/common.py
downleth/download.py
downleth/mpeg.py
downleth/schedule.py
downleth/stream.py
downleth/watch.py
downleth-1.2.dist-info/LICENSE
downleth-1.2.dist-info/METADATA
downleth-1.2.dist-info/WHEEL
downleth-1.2.dist-info/entry_points.txt
downleth-1.2.dist-info/top_level.txt
downleth-1.2.dist-info/RECORD
