Metadata-Version: 2.1
Name: downleth
Version: 1.2
Summary: downleth: Download ETH streams
Home-page: https://github.com/thomasgassmann/downleth
Author: Thomas Gassmann
Author-email: thomas@gassmann.dev
License: MIT
Keywords: downleth eth livestream
Platform: UNKNOWN
Classifier: Programming Language :: Python :: 3
Classifier: License :: OSI Approved :: MIT License
License-File: LICENSE
Requires-Dist: aiofiles (==22.1.0)
Requires-Dist: aiohttp (==3.8.1)
Requires-Dist: aiosignal (==1.2.0)
Requires-Dist: async-timeout (==4.0.2)
Requires-Dist: attrs (==22.1.0)
Requires-Dist: charset-normalizer (==2.1.1)
Requires-Dist: click (==8.1.3)
Requires-Dist: frozenlist (==1.3.1)
Requires-Dist: idna (==3.4)
Requires-Dist: iso8601 (==1.0.2)
Requires-Dist: m3u8 (==3.3.0)
Requires-Dist: multidict (==6.0.2)
Requires-Dist: pyee (==9.0.4)
Requires-Dist: python-ffmpeg (==1.0.14)
Requires-Dist: pytz (==2022.2.1)
Requires-Dist: typing-extensions (==4.3.0)
Requires-Dist: yarl (==1.8.1)
